codex/__init__.py
codex/__main__.py
codex/config.py
codex/core.py
vscodex-0.1.0.dist-info/DESCRIPTION.rst
vscodex-0.1.0.dist-info/METADATA
vscodex-0.1.0.dist-info/RECORD
vscodex-0.1.0.dist-info/WHEEL
vscodex-0.1.0.dist-info/entry_points.txt
vscodex-0.1.0.dist-info/metadata.json
vscodex-0.1.0.dist-info/top_level.txt
