Metadata-Version: 2.0
Name: vscodex
Version: 0.1.0
Summary: VSCode Extension Manager
Home-page: UNKNOWN
Author: Cauê Baasch de Souza
Author-email: cauebs@protonmail.com
License: MIT
Platform: UNKNOWN
Classifier: Environment :: Console
Classifier: License :: OSI Approved :: MIT License
Classifier: Programming Language :: Python
Classifier: Programming Language :: Python :: 3
Classifier: Programming Language :: Python :: 3.6
Classifier: Programming Language :: Python :: 3.7
Classifier: Programming Language :: Python :: 3 :: Only
Requires-Dist: docopt
Requires-Dist: requests
Requires-Dist: bs4
Requires-Dist: semver
Requires-Dist: tqdm
